mincli/__init__.py
mincli-0.2.1.dist-info/METADATA
mincli-0.2.1.dist-info/RECORD
mincli-0.2.1.dist-info/WHEEL
mincli-0.2.1.dist-info/entry_points.txt
mincli-0.2.1.dist-info/top_level.txt
